pyformlang/__init__.py
pyformlang/cfg/__init__.py
pyformlang/cfg/cfg.py
pyformlang/cfg/cfg_object.py
pyformlang/cfg/cyk_table.py
pyformlang/cfg/epsilon.py
pyformlang/cfg/llone_parser.py
pyformlang/cfg/parse_tree.py
pyformlang/cfg/pda_object_creator.py
pyformlang/cfg/production.py
pyformlang/cfg/recursive_decent_parser.py
pyformlang/cfg/set_queue.py
pyformlang/cfg/terminal.py
pyformlang/cfg/utils.py
pyformlang/cfg/utils_cfg.py
pyformlang/cfg/variable.py
pyformlang/cfg/tests/__init__.py
pyformlang/cfg/tests/test_cfg.py
pyformlang/cfg/tests/test_llone_parser.py
pyformlang/cfg/tests/test_production.py
pyformlang/cfg/tests/test_recursive_decent_parser.py
pyformlang/cfg/tests/test_terminal.py
pyformlang/cfg/tests/test_variable.py
pyformlang/fcfg/__init__.py
pyformlang/fcfg/fcfg.py
pyformlang/fcfg/feature_production.py
pyformlang/fcfg/feature_structure.py
pyformlang/fcfg/state.py
pyformlang/fcfg/tests/__init__.py
pyformlang/fcfg/tests/test_fcfg.py
pyformlang/fcfg/tests/test_feature_structure.py
pyformlang/finite_automaton/__init__.py
pyformlang/finite_automaton/deterministic_finite_automaton.py
pyformlang/finite_automaton/doubly_linked_list.py
pyformlang/finite_automaton/doubly_linked_node.py
pyformlang/finite_automaton/epsilon.py
pyformlang/finite_automaton/epsilon_nfa.py
pyformlang/finite_automaton/finite_automaton.py
pyformlang/finite_automaton/finite_automaton_object.py
pyformlang/finite_automaton/hopcroft_processing_list.py
pyformlang/finite_automaton/nondeterministic_finite_automaton.py
pyformlang/finite_automaton/nondeterministic_transition_function.py
pyformlang/finite_automaton/partition.py
pyformlang/finite_automaton/regexable.py
pyformlang/finite_automaton/state.py
pyformlang/finite_automaton/symbol.py
pyformlang/finite_automaton/transition_function.py
pyformlang/finite_automaton/tests/__init__.py
pyformlang/finite_automaton/tests/test_deterministic_finite_automaton.py
pyformlang/finite_automaton/tests/test_epsilon.py
pyformlang-1.0.10.dist-info/LICENSE
pyformlang-1.0.10.dist-info/METADATA
pyformlang-1.0.10.dist-info/WHEEL
pyformlang-1.0.10.dist-info/top_level.txt
pyformlang-1.0.10.dist-info/RECORD
