Metadata-Version: 2.1
Name: pyformlang
Version: 1.0.10
Summary: A python framework for formal grammars
Home-page: https://github.com/Aunsiels/pyformlang
Author: Julien Romero
Author-email: romerojulien34@gmail.com
Classifier: Programming Language :: Python :: 3
Classifier: License :: OSI Approved :: MIT License
Classifier: Operating System :: OS Independent
License-File: LICENSE
